nf.py
tests/__init__.py
tests/test_main.py
nf-1.4.0.dist-info/LICENSE
nf-1.4.0.dist-info/METADATA
nf-1.4.0.dist-info/WHEEL
nf-1.4.0.dist-info/entry_points.txt
nf-1.4.0.dist-info/top_level.txt
nf-1.4.0.dist-info/RECORD
