Metadata-Version: 2.1
Name: nf
Version: 1.4.0
Summary: Simple command line tool to make notification after target program finished work
Home-page: https://github.com/NIC-MichalLabedzki/nf
Author: Michał Łabędzki
Author-email: michal.tomasz.labedzki@gmail.com
License: UNKNOWN
Platform: UNKNOWN
Classifier: Development Status :: 5 - Production/Stable
Classifier: Intended Audience :: Customer Service
Classifier: Intended Audience :: Developers
Classifier: License :: OSI Approved
Classifier: License :: Freely Distributable
Classifier: License :: Public Domain
Classifier: Operating System :: OS Independent
Classifier: Programming Language :: Python
Classifier: Programming Language :: Python :: 2
Classifier: Programming Language :: Python :: 2.7
Classifier: Programming Language :: Python :: 3
Classifier: Programming Language :: Python :: 3.5
Classifier: Programming Language :: Python :: 3.6
Classifier: Programming Language :: Python :: 3.7
Classifier: Programming Language :: Python :: 3.8
Classifier: Programming Language :: Python :: Implementation :: CPython
Classifier: Programming Language :: Python :: Implementation :: Jython
Classifier: Programming Language :: Python :: Implementation :: PyPy
Requires-Dist: setuptools
Requires-Dist: win10toast-persist ; platform_system == "Windows"
Requires-Dist: paramiko ; platform_system == "Windows"
Requires-Dist: psutil ; platform_system == "Windows"
Provides-Extra: optionals
Requires-Dist: paramiko ; extra == 'optionals'
Requires-Dist: plyer ; extra == 'optionals'
Requires-Dist: psutil ; extra == 'optionals'
